keeks/__init__.py
keeks/bankroll.py
keeks/utils.py
keeks/binary_strategies/__init__.py
keeks/binary_strategies/base.py
keeks/binary_strategies/kelly.py
keeks/binary_strategies/simple.py
keeks/simulators/__init__.py
keeks/simulators/random_binary.py
keeks/simulators/random_uncertain_binary.py
keeks/simulators/repeated_binary.py
keeks-0.3.0.dist-info/METADATA
keeks-0.3.0.dist-info/WHEEL
keeks-0.3.0.dist-info/licenses/LICENSE.md
keeks-0.3.0.dist-info/RECORD
